shirotsubaki/__init__.py
shirotsubaki/element.py
shirotsubaki/report.py
shirotsubaki/style.py
shirotsubaki/templates/report.html
shirotsubaki/templates/report_with_tabs.html
shirotsubaki/utils/__init__.py
shirotsubaki-0.0.1a7.dist-info/METADATA
shirotsubaki-0.0.1a7.dist-info/WHEEL
shirotsubaki-0.0.1a7.dist-info/licenses/LICENSE
shirotsubaki-0.0.1a7.dist-info/RECORD
