Metadata-Version: 2.4
Name: shirotsubaki
Version: 0.0.1a7
Summary: This package is being developed to help generate beautiful reports.
Project-URL: GitHub, https://github.com/CookieBox26/shirotsubaki
Project-URL: Documentation, https://shirotsubaki.readthedocs.io/en/latest/
Author-email: CookieBox26 <cookie-box@cookie-box.info>
License-Expression: MIT
License-File: LICENSE
Classifier: License :: OSI Approved :: MIT License
Classifier: Operating System :: OS Independent
Classifier: Programming Language :: Python :: 3
Requires-Python: >=3.10
Requires-Dist: jinja2
Requires-Dist: numpy
Provides-Extra: docs
Requires-Dist: mkdocs; extra == 'docs'
Requires-Dist: mkdocs-material; extra == 'docs'
Requires-Dist: mkdocstrings-python; extra == 'docs'
Provides-Extra: test
Requires-Dist: matplotlib; extra == 'test'
Requires-Dist: pandas; extra == 'test'
Requires-Dist: pytest; extra == 'test'
